ctf/__init__.py
ctf/api.py
ctf/error.py
ctf/io.py
ctf/pieces.py
ctf/rendering.py
ctf/version.py
ctf/__pycache__/__init__.cpython-38.pyc
ctf/__pycache__/api.cpython-38.pyc
ctf/__pycache__/error.cpython-38.pyc
ctf/__pycache__/io.cpython-38.pyc
ctf/__pycache__/pieces.cpython-38.pyc
ctf/__pycache__/version.cpython-38.pyc
ctf/resources/PressStart2P-Regular.ttf
tests/__init__.py
tests/test_api.py
capture_the_flag-0.0.4.dist-info/LICENSE
capture_the_flag-0.0.4.dist-info/METADATA
capture_the_flag-0.0.4.dist-info/WHEEL
capture_the_flag-0.0.4.dist-info/top_level.txt
capture_the_flag-0.0.4.dist-info/RECORD
