Metadata-Version: 2.1
Name: capture-the-flag
Version: 0.0.4
Summary: A Capture The Flag (CTF) environment.
Home-page: https://github.com/documentedai/capture-the-flag
Author: Christian Lang
Author-email: me@christianlang.io
License: BSD
Download-URL: https://pypi.org/project/capture-the-flag/
Project-URL: Documentation, https://capture-the-flag.readthedocs.io/en/latest/
Project-URL: Source, https://github.com/documentedai/capture-the-flag
Project-URL: Tracker, https://github.com/documentedai/capture-the-flag/issues
Platform: UNKNOWN
Classifier: Development Status :: 5 - Production/Stable
Classifier: Programming Language :: Python :: 3
Classifier: Operating System :: OS Independent
Requires-Dist: numpy
Requires-Dist: pyglet
Provides-Extra: docs
Requires-Dist: sphinx ; extra == 'docs'
Provides-Extra: testing
Requires-Dist: pytest ; extra == 'testing'
Requires-Dist: pytest-cov ; extra == 'testing'
Requires-Dist: flake8 ; extra == 'testing'
